nhdnet/__init__.py
nhdnet/io.py
nhdnet/geometry/__init__.py
nhdnet/geometry/lines.py
nhdnet/geometry/points.py
nhdnet/geometry/polygons.py
nhdnet/nhd/__init__.py
nhdnet/nhd/cut.py
nhdnet/nhd/download.py
nhdnet/nhd/extract.py
nhdnet/nhd/network.py
nhdnet/nhd/legacy/__init__.py
nhdnet/nhd/legacy/download.py
nhdnet/nhd/legacy/extract.py
nhdnet-0.2.0.dist-info/LICENSE
nhdnet-0.2.0.dist-info/METADATA
nhdnet-0.2.0.dist-info/WHEEL
nhdnet-0.2.0.dist-info/top_level.txt
nhdnet-0.2.0.dist-info/RECORD
