Metadata-Version: 2.1
Name: nhdnet
Version: 0.2.0
Summary: US National Hydrography Dataset Network and Barrier Analysis Tools
Home-page: https://github.com/brendan-ward/nhdnet
Author: Brendan C. Ward
License: UNKNOWN
Keywords: nhd hydrography
Platform: UNKNOWN
Classifier: Development Status :: 3 - Alpha
Classifier: License :: OSI Approved :: MIT License
Classifier: Programming Language :: Python :: 3.6
Requires-Dist: pandas
Requires-Dist: geopandas
Requires-Dist: rtree
Requires-Dist: geofeather
Requires-Dist: requests
Provides-Extra: dev
Requires-Dist: black ; extra == 'dev'
Requires-Dist: pylint ; extra == 'dev'
Provides-Extra: test
Requires-Dist: pytest ; extra == 'test'
Requires-Dist: pytest-cov ; extra == 'test'
